slacgs/__init__.py
slacgs/demo.py
slacgs/enumtypes.py
slacgs/gdrive_client.py
slacgs/gspread_client.py
slacgs/model.py
slacgs/report.py
slacgs/simulator.py
slacgs/utils.py
slacgs-0.1.9.dist-info/LICENSE
slacgs-0.1.9.dist-info/METADATA
slacgs-0.1.9.dist-info/WHEEL
slacgs-0.1.9.dist-info/top_level.txt
slacgs-0.1.9.dist-info/RECORD
